powerline_svnstatus/__init__.py
powerline_svnstatus/segments.py
powerline_svnstatus-0.6.dist-info/DESCRIPTION.rst
powerline_svnstatus-0.6.dist-info/METADATA
powerline_svnstatus-0.6.dist-info/RECORD
powerline_svnstatus-0.6.dist-info/WHEEL
powerline_svnstatus-0.6.dist-info/metadata.json
powerline_svnstatus-0.6.dist-info/top_level.txt
