Metadata-Version: 2.0
Name: powerline-svnstatus
Version: 0.6
Summary: A Powerline segment for showing the status of a Subversion working directory
Home-page: https://github.com/justinludwig/powerline-svnstatus
Author: Justin Ludwig
Author-email: justin@ldwg.us
License: MIT
Keywords: powerline svn status prompt
Platform: UNKNOWN
Classifier: Environment :: Console
Classifier: Intended Audience :: Developers
Classifier: License :: OSI Approved :: MIT License
Classifier: Topic :: Terminals
